Workbook

Sheet Items
A1: SKU | B1: Description | C1: Type | D1: UoM | E1: Std Cost | F1: List Price | G1: Lead Time (d) | H1: Reorder Pt | I1: Default Supplier | J1: Last Updated
A2: FG-1001 | B2: Industrial Pump Assembly Mk II | C2: Finished | D2: EA | E2: 412.5 | F2: 925 | G2: 21 | H2: 25 | I2: Internal Production | J2: 2026-04-12
A3: FG-1002 | B3: Industrial Pump Assembly Mk III | C3: Finished | D3: EA | E3: 478.2 | F3: 1095 | G3: 28 | H3: 18 | I3: Internal Production | J3: 2026-04-12
A4: FG-1101 | B4: Hydraulic Cylinder 250mm | C4: Finished | D4: EA | E4: 188.75 | F4: 415 | G4: 14 | H4: 40 | I4: Internal Production | J4: 2026-04-08
A5: FG-1102 | B5: Hydraulic Cylinder 400mm | C5: Finished | D5: EA | E5: 252.1 | F5: 565 | G5: 17 | H5: 30 | I5: Internal Production | J5: 2026-04-08
A6: FG-1203 | B6: Gearbox Reduction Unit 30:1 | C6: Finished | D6: EA | E6: 318.4 | F6: 740 | G6: 24 | H6: 22 | I6: Internal Production | J6: 2026-03-29
A7: SA-2010 | B7: Pump Housing Cast (Machined) | C7: WIP | D7: EA | E7: 92.3 | G7: 10 | H7: 60 | I7: Acme Castings GmbH | J7: 2026-04-02
A8: SA-2011 | B8: Impeller, Stainless 316L | C8: WIP | D8: EA | E8: 64.8 | G8: 8 | H8: 80 | I8: NorthSteel Foundry | J8: 2026-04-02
A9: SA-2012 | B9: Cylinder Tube, Honed | C9: WIP | D9: EA | E9: 71.2 | G9: 12 | H9: 50 | I9: PrecisionBore Ltd | J9: 2026-03-30
A10: SA-2013 | B10: Piston Rod, Chrome-plated | C10: WIP | D10: EA | E10: 38.55 | G10: 9 | H10: 75 | I10: PrecisionBore Ltd | J10: 2026-03-30
A11: RM-3001 | B11: Cast Iron GG25 — 50kg ingot | C11: Raw | D11: KG | E11: 1.85 | G11: 14 | H11: 1500 | I11: Acme Castings GmbH | J11: 2026-04-15
A12: RM-3002 | B12: Stainless 316L bar — 60mm | C12: Raw | D12: M | E12: 14.2 | G12: 18 | H12: 200 | I12: NorthSteel Foundry | J12: 2026-04-15
A13: RM-3003 | B13: Steel Plate S355 — 8mm | C13: Raw | D13: M2 | E13: 28.6 | G13: 10 | H13: 80 | I13: EuroSteel SA | J13: 2026-04-10
A14: RM-3010 | B14: NBR O-ring 25mm ID | C14: Raw | D14: EA | E14: 0.18 | G14: 5 | H14: 5000 | I14: SealPro AG | J14: 2026-04-18
A15: RM-3011 | B15: NBR O-ring 50mm ID | C15: Raw | D15: EA | E15: 0.31 | G15: 5 | H15: 4000 | I15: SealPro AG | J15: 2026-04-18
A16: RM-3020 | B16: M10x40 Hex Bolt, A2-70 | C16: Raw | D16: EA | E16: 0.22 | G16: 7 | H16: 10000 | I16: FastenAll Co | J16: 2026-04-05
A17: RM-3021 | B17: M12x50 Hex Bolt, A2-70 | C17: Raw | D17: EA | E17: 0.34 | G17: 7 | H17: 8000 | I17: FastenAll Co | J17: 2026-04-05
A18: RM-3030 | B18: Ball Bearing 6205-2RS | C18: Raw | D18: EA | E18: 4.85 | G18: 12 | H18: 600 | I18: BearingsDirect EU | J18: 2026-04-01
... A21: RM-3050 | B21: Powder Coat, Industrial Blue | C21: Raw | D21: KG | E21: 12.4 | G21: 14 | H21: 120 | I21: CoatTech sro | J21: 2026-04-09

Sheet BOM
A1: Parent SKU | B1: Parent Description | C1: Component SKU | D1: Component Description | E1: Qty per Parent | F1: UoM | G1: Scrap % | H1: Effective Qty | I1: Unit Cost | J1: Extended Cost
A2: FG-1001 | B2: Industrial Pump Assembly Mk II | C2: SA-2010 | D2: Pump Housing Cast (Machined) | E2: 1 | F2: EA | G2: 0.02 | H2: =E2*(1+G2) | I2: 92.3 | J2: =H2*I2
A3: FG-1001 | B3: Industrial Pump Assembly Mk II | C3: SA-2011 | D3: Impeller, Stainless 316L | E3: 1 | F3: EA | G3: 0.03 | H3: =E3*(1+G3) | I3: 64.8 | J3: =H3*I3
A4: FG-1001 | B4: Industrial Pump Assembly Mk II | C4: RM-3010 | D4: NBR O-ring 25mm ID | E4: 4 | F4: EA | G4: 0.05 | H4: =E4*(1+G4) | I4: 0.18 | J4: =H4*I4
A5: FG-1001 | B5: Industrial Pump Assembly Mk II | C5: RM-3020 | D5: M10x40 Hex Bolt, A2-70 | E5: 8 | F5: EA | G5: 0.01 | H5: =E5*(1+G5) | I5: 0.22 | J5: =H5*I5
A6: FG-1001 | B6: Industrial Pump Assembly Mk II | C6: RM-3030 | D6: Ball Bearing 6205-2RS | E6: 2 | F6: EA | G6: 0.01 | H6: =E6*(1+G6) | I6: 4.85 | J6: =H6*I6
A7: FG-1001 | B7: Industrial Pump Assembly Mk II | C7: RM-3040 | D7: Hydraulic Oil ISO VG46 — 20L | E7: 0.8 | F7: L | G7: 0.04 | H7: =E7*(1+G7) | I7: 3.85 | J7: =H7*I7
A8: FG-1001 | B8: Industrial Pump Assembly Mk II | C8: RM-3050 | D8: Powder Coat, Industrial Blue | E8: 0.4 | F8: KG | G8: 0.06 | H8: =E8*(1+G8) | I8: 12.4 | J8: =H8*I8
A9: FG-1002 | B9: Industrial Pump Assembly Mk III | C9: SA-2010 | D9: Pump Housing Cast (Machined) | E9: 1 | F9: EA | G9: 0.02 | H9: =E9*(1+G9) | I9: 92.3 | J9: =H9*I9
A10: FG-1002 | B10: Industrial Pump Assembly Mk III | C10: SA-2011 | D10: Impeller, Stainless 316L | E10: 1 | F10: EA | G10: 0.03 | H10: =E10*(1+G10) | I10: 64.8 | J10: =H10*I10
A11: FG-1002 | B11: Industrial Pump Assembly Mk III | C11: RM-3011 | D11: NBR O-ring 50mm ID | E11: 4 | F11: EA | G11: 0.05 | H11: =E11*(1+G11) | I11: 0.31 | J11: =H11*I11
A12: FG-1002 | B12: Industrial Pump Assembly Mk III | C12: RM-3021 | D12: M12x50 Hex Bolt, A2-70 | E12: 8 | F12: EA | G12: 0.01 | H12: =E12*(1+G12) | I12: 0.34 | J12: =H12*I12
A13: FG-1002 | B13: Industrial Pump Assembly Mk III | C13: RM-3031 | D13: Ball Bearing 6305-2RS | E13: 2 | F13: EA | G13: 0.01 | H13: =E13*(1+G13) | I13: 7.4 | J13: =H13*I13
... A34: SA-2013 | B34: Piston Rod, Chrome-plated | C34: RM-3002 | D34: Stainless 316L bar — 60mm | E34: 0.25 | F34: M | G34: 0.06 | H34: =E34*(1+G34) | I34: 14.2 | J34: =H34*I34

Sheet Inventory
A1: SKU | B1: Description | C1: Warehouse | D1: On Hand | E1: Allocated | F1: Available | G1: Reorder Pt | H1: Status | I1: Unit Cost | J1: Inventory Value | K1: Last Count
A2: FG-1001 | B2: Industrial Pump Assembly Mk II | C2: WH-MAIN | D2: 42 | E2: 15 | F2: =D2-E2 | G2: 25 | H2: =IF(F2<G2,"REORDER","OK") | I2: 412.5 | J2: =D2*I2 | K2: 46128.917
A3: FG-1001 | B3: Industrial Pump Assembly Mk II | C3: WH-SOUTH | D3: 18 | E3: 0 | F3: =D3-E3 | G3: 25 | H3: =IF(F3<G3,"REORDER","OK") | I3: 412.5 | J3: =D3*I3 | K3: 46129.917
A4: FG-1001 | B4: Industrial Pump Assembly Mk II | C4: WH-EU2 | D4: 6 | E4: 0 | F4: =D4-E4 | G4: 25 | H4: =IF(F4<G4,"REORDER","OK") | I4: 412.5 | J4: =D4*I4 | K4: 46130.917
A5: FG-1002 | B5: Industrial Pump Assembly Mk III | C5: WH-MAIN | D5: 12 | E5: 8 | F5: =D5-E5 | G5: 18 | H5: =IF(F5<G5,"REORDER","OK") | I5: 478.2 | J5: =D5*I5 | K5: 46131.917
A6: FG-1002 | B6: Industrial Pump Assembly Mk III | C6: WH-SOUTH | D6: 4 | E6: 0 | F6: =D6-E6 | G6: 18 | H6: =IF(F6<G6,"REORDER","OK") | I6: 478.2 | J6: =D6*I6 | K6: 46132.917
A7: FG-1002 | B7: Industrial Pump Assembly Mk III | C7: WH-EU2 | D7: 2 | E7: 0 | F7: =D7-E7 | G7: 18 | H7: =IF(F7<G7,"REORDER","OK") | I7: 478.2 | J7: =D7*I7 | K7: 46133.917
A8: FG-1101 | B8: Hydraulic Cylinder 250mm | C8: WH-MAIN | D8: 62 | E8: 22 | F8: =D8-E8 | G8: 40 | H8: =IF(F8<G8,"REORDER","OK") | I8: 188.75 | J8: =D8*I8 | K8: 46134.917
A9: FG-1101 | B9: Hydraulic Cylinder 250mm | C9: WH-SOUTH | D9: 30 | E9: 0 | F9: =D9-E9 | G9: 40 | H9: =IF(F9<G9,"REORDER","OK") | I9: 188.75 | J9: =D9*I9 | K9: 46135.917
A10: FG-1101 | B10: Hydraulic Cylinder 250mm | C10: WH-EU2 | D10: 14 | E10: 0 | F10: =D10-E10 | G10: 40 | H10: =IF(F10<G10,"REORDER","OK") | I10: 188.75 | J10: =D10*I10 | K10: 46126.917
A11: FG-1102 | B11: Hydraulic Cylinder 400mm | C11: WH-MAIN | D11: 38 | E11: 18 | F11: =D11-E11 | G11: 30 | H11: =IF(F11<G11,"REORDER","OK") | I11: 252.1 | J11: =D11*I11 | K11: 46127.917
A12: FG-1102 | B12: Hydraulic Cylinder 400mm | C12: WH-SOUTH | D12: 12 | E12: 0 | F12: =D12-E12 | G12: 30 | H12: =IF(F12<G12,"REORDER","OK") | I12: 252.1 | J12: =D12*I12 | K12: 46128.917
A13: FG-1102 | B13: Hydraulic Cylinder 400mm | C13: WH-EU2 | D13: 8 | E13: 0 | F13: =D13-E13 | G13: 30 | H13: =IF(F13<G13,"REORDER","OK") | I13: 252.1 | J13: =D13*I13 | K13: 46129.917
... A31: RM-3050 | B31: Powder Coat, Industrial Blue | C31: WH-MAIN | D31: 180 | E31: 35 | F31: =D31-E31 | G31: 120 | H31: =IF(F31<G31,"REORDER","OK") | I31: 12.4 | J31: =D31*I31 | K31: 46127.917
A32: TOTAL | D32: =SUM(D2:D31) | E32: =SUM(E2:E31) | F32: =SUM(F2:F31) | J32: =SUM(J2:J31)

Sheet Sales Orders
A1: SO # | B1: Order Date | C1: Customer | D1: Country | E1: SKU | F1: Description | G1: Qty | H1: Unit Price | I1: Discount % | J1: Net Total | K1: VAT % | L1: VAT Amount | M1: Gross Total | N1: Status | O1: Due Date
A2: SO-2026-0421 | B2: 46114 | C2: Brno Industrial Pumps as | D2: CZ | E2: FG-1001 | F2: Industrial Pump Assembly Mk II | G2: 8 | H2: 925 | I2: 0.05 | J2: =G2*H2*(1-I2) | K2: 0.21 | L2: =J2*K2 | M2: =J2+L2 | N2: Invoiced | O2: 46144
A3: SO-2026-0422 | B3: 46115 | C3: Brno Industrial Pumps as | D3: CZ | E3: FG-1101 | F3: Hydraulic Cylinder 250mm | G3: 12 | H3: 415 | I3: 0.05 | J3: =G3*H3*(1-I3) | K3: 0.21 | L3: =J3*K3 | M3: =J3+L3 | N3: Invoiced | O3: 46145
A4: SO-2026-0423 | B4: 46117 | C4: Bavaria Hydraulik GmbH | D4: DE | E4: FG-1102 | F4: Hydraulic Cylinder 400mm | G4: 6 | H4: 565 | I4: 0.1 | J4: =G4*H4*(1-I4) | K4: 0.19 | L4: =J4*K4 | M4: =J4+L4 | N4: Invoiced | O4: 46147
A5: SO-2026-0424 | B5: 46120 | C5: Bavaria Hydraulik GmbH | D5: DE | E5: FG-1002 | F5: Industrial Pump Assembly Mk III | G5: 4 | H5: 1095 | I5: 0.1 | J5: =G5*H5*(1-I5) | K5: 0.19 | L5: =J5*K5 | M5: =J5+L5 | N5: Invoiced | O5: 46150
A6: SO-2026-0425 | B6: 46122 | C6: Polskie Maszyny Sp.z.o.o. | D6: PL | E6: FG-1203 | F6: Gearbox Reduction Unit 30:1 | G6: 3 | H6: 740 | I6: 0 | J6: =G6*H6*(1-I6) | K6: 0.23 | L6: =J6*K6 | M6: =J6+L6 | N6: Shipped | O6: 46152
A7: SO-2026-0426 | B7: 46124 | C7: Polskie Maszyny Sp.z.o.o. | D7: PL | E7: FG-1001 | F7: Industrial Pump Assembly Mk II | G7: 10 | H7: 925 | I7: 0.07 | J7: =G7*H7*(1-I7) | K7: 0.23 | L7: =J7*K7 | M7: =J7+L7 | N7: Shipped | O7: 46154
A8: SO-2026-0427 | B8: 46127 | C8: Iberian Marine SL | D8: ES | E8: FG-1101 | F8: Hydraulic Cylinder 250mm | G8: 20 | H8: 415 | I8: 0.08 | J8: =G8*H8*(1-I8) | K8: 0.21 | L8: =J8*K8 | M8: =J8+L8 | N8: Shipped | O8: 46157
A9: SO-2026-0428 | B9: 46130 | C9: Iberian Marine SL | D9: ES | E9: FG-1102 | F9: Hydraulic Cylinder 400mm | G9: 8 | H9: 565 | I9: 0.08 | J9: =G9*H9*(1-I9) | K9: 0.21 | L9: =J9*K9 | M9: =J9+L9 | N9: Confirmed | O9: 46160
A10: SO-2026-0429 | B10: 46133 | C10: Nordic OEM AB | D10: SE | E10: FG-1001 | F10: Industrial Pump Assembly Mk II | G10: 14 | H10: 925 | I10: 0.03 | J10: =G10*H10*(1-I10) | K10: 0.25 | L10: =J10*K10 | M10: =J10+L10 | N10: Confirmed | O10: 46163
A11: SO-2026-0430 | B11: 46135 | C11: Nordic OEM AB | D11: SE | E11: FG-1203 | F11: Gearbox Reduction Unit 30:1 | G11: 5 | H11: 740 | I11: 0 | J11: =G11*H11*(1-I11) | K11: 0.25 | L11: =J11*K11 | M11: =J11+L11 | N11: Confirmed | O11: 46165
A12: SO-2026-0431 | B12: 46137 | C12: Adriatic Pumps doo | D12: HR | E12: FG-1002 | F12: Industrial Pump Assembly Mk III | G12: 6 | H12: 1095 | I12: 0.06 | J12: =G12*H12*(1-I12) | K12: 0.25 | L12: =J12*K12 | M12: =J12+L12 | N12: Quotation | O12: 46167
A13: SO-2026-0432 | B13: 46140 | C13: Adriatic Pumps doo | D13: HR | E13: FG-1101 | F13: Hydraulic Cylinder 250mm | G13: 18 | H13: 415 | I13: 0.06 | J13: =G13*H13*(1-I13) | K13: 0.25 | L13: =J13*K13 | M13: =J13+L13 | N13: Quotation | O13: 46170
... A15: SO-2026-0434 | B15: 46147 | C15: Helvetica Mechanik AG | D15: CH | E15: FG-1203 | F15: Gearbox Reduction Unit 30:1 | G15: 6 | H15: 740 | I15: 0.04 | J15: =G15*H15*(1-I15) | K15: 0.077 | L15: =J15*K15 | M15: =J15+L15 | N15: Quotation | O15: 46177
A16: TOTAL | J16: =SUM(J2:J15) | L16: =SUM(L2:L15) | M16: =SUM(M2:M15)

Sheet Purchase Orders
A1: PO # | B1: Order Date | C1: Supplier | D1: SKU | E1: Description | F1: Qty | G1: Unit Cost | H1: Net Total | I1: Expected Receipt | J1: Status
A2: PO-2026-3110 | B2: 46116 | C2: Acme Castings GmbH | D2: RM-3001 | E2: Cast Iron GG25 — 50kg ingot | F2: 4000 | G2: 1.85 | H2: =F2*G2 | I2: 46134 | J2: Received
A3: PO-2026-3111 | B3: 46117 | C3: NorthSteel Foundry | D3: RM-3002 | E3: Stainless 316L bar — 60mm | F3: 600 | G3: 14.2 | H3: =F3*G3 | I3: 46137 | J3: Received
A4: PO-2026-3112 | B4: 46118 | C4: EuroSteel SA | D4: RM-3003 | E4: Steel Plate S355 — 8mm | F4: 220 | G4: 28.6 | H4: =F4*G4 | I4: 46130 | J4: Received
A5: PO-2026-3113 | B5: 46121 | C5: SealPro AG | D5: RM-3010 | E5: NBR O-ring 25mm ID | F5: 12000 | G5: 0.18 | H5: =F5*G5 | I5: 46127 | J5: Received
A6: PO-2026-3114 | B6: 46121 | C6: SealPro AG | D6: RM-3011 | E6: NBR O-ring 50mm ID | F6: 10000 | G6: 0.31 | H6: =F6*G6 | I6: 46127 | J6: Received
A7: PO-2026-3115 | B7: 46123 | C7: FastenAll Co | D7: RM-3020 | E7: M10x40 Hex Bolt, A2-70 | F7: 30000 | G7: 0.22 | H7: =F7*G7 | I7: 46132 | J7: Received
A8: PO-2026-3116 | B8: 46123 | C8: FastenAll Co | D8: RM-3021 | E8: M12x50 Hex Bolt, A2-70 | F8: 24000 | G8: 0.34 | H8: =F8*G8 | I8: 46132 | J8: Received
A9: PO-2026-3117 | B9: 46127 | C9: BearingsDirect EU | D9: RM-3030 | E9: Ball Bearing 6205-2RS | F9: 1200 | G9: 4.85 | H9: =F9*G9 | I9: 46141 | J9: In Transit
A10: PO-2026-3118 | B10: 46127 | C10: BearingsDirect EU | D10: RM-3031 | E10: Ball Bearing 6305-2RS | F10: 800 | G10: 7.4 | H10: =F10*G10 | I10: 46141 | J10: In Transit
A11: PO-2026-3119 | B11: 46130 | C11: LubricaChem | D11: RM-3040 | E11: Hydraulic Oil ISO VG46 — 20L | F11: 1600 | G11: 3.85 | H11: =F11*G11 | I11: 46135 | J11: Received
A12: PO-2026-3120 | B12: 46132 | C12: CoatTech sro | D12: RM-3050 | E12: Powder Coat, Industrial Blue | F12: 240 | G12: 12.4 | H12: =F12*G12 | I12: 46148 | J12: Confirmed
A13: PO-2026-3121 | B13: 46138 | C13: Acme Castings GmbH | D13: RM-3001 | E13: Cast Iron GG25 — 50kg ingot | F13: 5000 | G13: 1.85 | H13: =F13*G13 | I13: 46154 | J13: Confirmed
A14: PO-2026-3122 | B14: 46144 | C14: NorthSteel Foundry | D14: RM-3002 | E14: Stainless 316L bar — 60mm | F14: 700 | G14: 14.2 | H14: =F14*G14 | I14: 46164 | J14: Draft
A15: TOTAL | H15: =SUM(H2:H14)

Sheet Production
A1: WO # | B1: SKU | C1: Description | D1: Qty Planned | E1: Qty Produced | F1: % Complete | G1: Work Center | H1: Start Date | I1: Due Date | J1: Status | K1: Std Cost | L1: WIP Value
A2: WO-2026-0801 | B2: FG-1001 | C2: Industrial Pump Assembly Mk II | D2: 30 | E2: 30 | F2: =IFERROR(E2/D2,0) | G2: WC-ASSY-1 | H2: 46106 | I2: 46120 | J2: Done | K2: 412.5 | L2: =E2*K2
A3: WO-2026-0802 | B3: FG-1101 | C3: Hydraulic Cylinder 250mm | D3: 60 | E3: 60 | F3: =IFERROR(E3/D3,0) | G3: WC-MACH-2 | H3: 46109 | I3: 46123 | J3: Done | K3: 188.75 | L3: =E3*K3
A4: WO-2026-0803 | B4: FG-1002 | C4: Industrial Pump Assembly Mk III | D4: 16 | E4: 12 | F4: =IFERROR(E4/D4,0) | G4: WC-ASSY-1 | H4: 46117 | I4: 46134 | J4: In Progress | K4: 478.2 | L4: =E4*K4
A5: WO-2026-0804 | B5: FG-1102 | C5: Hydraulic Cylinder 400mm | D5: 24 | E5: 18 | F5: =IFERROR(E5/D5,0) | G5: WC-MACH-2 | H5: 46118 | I5: 46136 | J5: In Progress | K5: 252.1 | L5: =E5*K5
A6: WO-2026-0805 | B6: FG-1203 | C6: Gearbox Reduction Unit 30:1 | D6: 12 | E6: 0 | F6: =IFERROR(E6/D6,0) | G6: WC-ASSY-2 | H6: 46137 | I6: 46157 | J6: Scheduled | K6: 318.4 | L6: =E6*K6
A7: WO-2026-0806 | B7: FG-1001 | C7: Industrial Pump Assembly Mk II | D7: 40 | E7: 0 | F7: =IFERROR(E7/D7,0) | G7: WC-ASSY-1 | H7: 46144 | I7: 46162 | J7: Scheduled | K7: 412.5 | L7: =E7*K7
A8: WO-2026-0807 | B8: FG-1101 | C8: Hydraulic Cylinder 250mm | D8: 30 | E8: 0 | F8: =IFERROR(E8/D8,0) | G8: WC-MACH-2 | H8: 46152 | I8: 46168 | J8: Scheduled | K8: 188.75 | L8: =E8*K8
A9: WO-2026-0808 | B9: SA-2010 | C9: Pump Housing Cast (Machined) | D9: 200 | E9: 200 | F9: =IFERROR(E9/D9,0) | G9: WC-CAST | H9: 46113 | I9: 46124 | J9: Done | K9: 92.3 | L9: =E9*K9
A10: WO-2026-0809 | B10: SA-2011 | C10: Impeller, Stainless 316L | D10: 180 | E10: 120 | F10: =IFERROR(E10/D10,0) | G10: WC-CAST | H10: 46127 | I10: 46142 | J10: In Progress | K10: 64.8 | L10: =E10*K10

Sheet Trial Balance
A1: Account # | B1: Account Name | C1: Type | D1: Opening Balance | E1: Period Debit | F1: Period Credit | G1: Closing Balance
A2: 1010 | B2: Cash on Hand | C2: Asset | D2: 84200 | E2: 412800 | F2: 358900 | G2: =D2+E2-F2
A3: 1020 | B3: Bank — Operating | C3: Asset | D3: 312500 | E3: 1248000 | F3: 1192800 | G3: =D3+E3-F3
A4: 1110 | B4: Accounts Receivable | C4: Asset | D4: 218400 | E4: 624900 | F4: 561200 | G4: =D4+E4-F4
A5: 1210 | B5: Inventory — Raw Materials | C5: Asset | D5: 198600 | E5: 286400 | F5: 232100 | G5: =D5+E5-F5
A6: 1211 | B6: Inventory — WIP | C6: Asset | D6: 64200 | E6: 142800 | F6: 121500 | G6: =D6+E6-F6
A7: 1212 | B7: Inventory — Finished Goods | C7: Asset | D7: 312800 | E7: 421500 | F7: 384200 | G7: =D7+E7-F7
A8: 1510 | B8: Property, Plant & Equipment | C8: Asset | D8: 1820000 | E8: 28000 | F8: 0 | G8: =D8+E8-F8
A9: 1610 | B9: Accumulated Depreciation | C9: Asset | D9: -612000 | E9: 0 | F9: 24300 | G9: =D9+E9-F9
A10: 2010 | B10: Accounts Payable | C10: Liability | D10: -184300 | E10: 218600 | F10: 296400 | G10: =D10+E10-F10
A11: 2110 | B11: VAT Payable | C11: Liability | D11: -28400 | E11: 32100 | F11: 64200 | G11: =D11+E11-F11
A12: 2210 | B12: Payroll Payable | C12: Liability | D12: -42600 | E12: 184200 | F12: 192800 | G12: =D12+E12-F12
A13: 2510 | B13: Long-term Debt | C13: Liability | D13: -480000 | E13: 12000 | F13: 0 | G13: =D13+E13-F13
... A31: 7020 | B31: Tax Expense | C31: Expense | D31: 0 | E31: 32100 | F31: 0 | G31: =D31+E31-F31
A32: TOTAL | D32: =SUM(D2:D31) | E32: =SUM(E2:E31) | F32: =SUM(F2:F31) | G32: =SUM(G2:G31)

Sheet P&L
A1: Income Statement — Period 4 / 2026 | B1: Amount (EUR) | C1: % of Revenue
A2: Revenue
A3: Pumps | B3: =-VLOOKUP("4010",'Trial Balance'!A:G,7,FALSE) | C3: =IFERROR(B3/$B$7,0)
A4: Hydraulics | B4: =-VLOOKUP("4020",'Trial Balance'!A:G,7,FALSE) | C4: =IFERROR(B4/$B$7,0)
A5: Gearboxes | B5: =-VLOOKUP("4030",'Trial Balance'!A:G,7,FALSE) | C5: =IFERROR(B5/$B$7,0)
A6: Less: Discounts | B6: =-VLOOKUP("4910",'Trial Balance'!A:G,7,FALSE) | C6: =IFERROR(B6/$B$7,0)
A7: Net Revenue | B7: =SUM(B3:B6) | C7: =IFERROR(B7/$B$7,0)
A9: Cost of Goods Sold
A10: Materials | B10: =VLOOKUP("5010",'Trial Balance'!A:G,7,FALSE) | C10: =IFERROR(B10/$B$7,0)
A11: Direct Labor | B11: =VLOOKUP("5020",'Trial Balance'!A:G,7,FALSE) | C11: =IFERROR(B11/$B$7,0)
A12: Overhead | B12: =VLOOKUP("5030",'Trial Balance'!A:G,7,FALSE) | C12: =IFERROR(B12/$B$7,0)
A13: Total COGS | B13: =SUM(B10:B12) | C13: =IFERROR(B13/$B$7,0)
A15: Gross Profit | B15: =B7-B13 | C15: =IFERROR(B15/$B$7,0)
A16: Gross Margin % | B16: =B15/B7
A18: Operating Expenses
A19: Salaries & Wages | B19: =VLOOKUP("6010",'Trial Balance'!A:G,7,FALSE) | C19: =IFERROR(B19/$B$7,0)
A20: Rent & Utilities | B20: =VLOOKUP("6020",'Trial Balance'!A:G,7,FALSE) | C20: =IFERROR(B20/$B$7,0)
A21: Depreciation | B21: =VLOOKUP("6030",'Trial Balance'!A:G,7,FALSE) | C21: =IFERROR(B21/$B$7,0)
A22: Marketing & Sales | B22: =VLOOKUP("6040",'Trial Balance'!A:G,7,FALSE) | C22: =IFERROR(B22/$B$7,0)
A23: Travel & Entertainment | B23: =VLOOKUP("6050",'Trial Balance'!A:G,7,FALSE) | C23: =IFERROR(B23/$B$7,0)
A24: IT & Software | B24: =VLOOKUP("6060",'Trial Balance'!A:G,7,FALSE) | C24: =IFERROR(B24/$B$7,0)
A25: Other | B25: =VLOOKUP("6090",'Trial Balance'!A:G,7,FALSE) | C25: =IFERROR(B25/$B$7,0)
A26: Total OpEx | B26: =SUM(B19:B25) | C26: =IFERROR(B26/$B$7,0)
A28: Operating Income (EBIT) | B28: =B15-B26 | C28: =IFERROR(B28/$B$7,0)
A29: Operating Margin % | B29: =B28/B7
A31: Interest Expense | B31: =VLOOKUP("7010",'Trial Balance'!A:G,7,FALSE) | C31: =IFERROR(B31/$B$7,0)
A32: Pre-tax Income | B32: =B28-B31 | C32: =IFERROR(B32/$B$7,0)
A33: Tax Expense | B33: =VLOOKUP("7020",'Trial Balance'!A:G,7,FALSE) | C33: =IFERROR(B33/$B$7,0)
A34: Net Income | B34: =B32-B33 | C34: =IFERROR(B34/$B$7,0)
A35: Net Margin % | B35: =B34/B7

Sheet AR Aging
A1: Customer | B1: Invoice # | C1: Invoice Date | D1: Due Date | E1: Total | F1: Days Overdue | G1: 0–30 | H1: 31–60 | I1: 61–90 | J1: 90+
A2: Brno Industrial Pumps as | B2: INV-26-1042 | C2: 46093 | D2: 46123 | E2: 18420.5 | F2: =MAX(0,DATE(2026,5,14)-D2) | G2: =IF(F2<=30,E2,0) | H2: =IF(AND(F2>30,F2<=60),E2,0) | I2: =IF(AND(F2>60,F2<=90),E2,0) | J2: =IF(F2>90,E2,0)
A3: Brno Industrial Pumps as | B3: INV-26-1051 | C3: 46109 | D3: 46139 | E3: 9840 | F3: =MAX(0,DATE(2026,5,14)-D3) | G3: =IF(F3<=30,E3,0) | H3: =IF(AND(F3>30,F3<=60),E3,0) | I3: =IF(AND(F3>60,F3<=90),E3,0) | J3: =IF(F3>90,E3,0)
A4: Bavaria Hydraulik GmbH | B4: INV-26-1063 | C4: 46114 | D4: 46144 | E4: 24600 | F4: =MAX(0,DATE(2026,5,14)-D4) | G4: =IF(F4<=30,E4,0) | H4: =IF(AND(F4>30,F4<=60),E4,0) | I4: =IF(AND(F4>60,F4<=90),E4,0) | J4: =IF(F4>90,E4,0)
A5: Bavaria Hydraulik GmbH | B5: INV-26-1071 | C5: 46126 | D5: 46156 | E5: 14820 | F5: =MAX(0,DATE(2026,5,14)-D5) | G5: =IF(F5<=30,E5,0) | H5: =IF(AND(F5>30,F5<=60),E5,0) | I5: =IF(AND(F5>60,F5<=90),E5,0) | J5: =IF(F5>90,E5,0)
A6: Polskie Maszyny Sp.z.o.o. | B6: INV-26-1080 | C6: 46130 | D6: 46160 | E6: 12400 | F6: =MAX(0,DATE(2026,5,14)-D6) | G6: =IF(F6<=30,E6,0) | H6: =IF(AND(F6>30,F6<=60),E6,0) | I6: =IF(AND(F6>60,F6<=90),E6,0) | J6: =IF(F6>90,E6,0)
A7: Iberian Marine SL | B7: INV-26-1086 | C7: 46133 | D7: 46163 | E7: 18600 | F7: =MAX(0,DATE(2026,5,14)-D7) | G7: =IF(F7<=30,E7,0) | H7: =IF(AND(F7>30,F7<=60),E7,0) | I7: =IF(AND(F7>60,F7<=90),E7,0) | J7: =IF(F7>90,E7,0)
A8: Nordic OEM AB | B8: INV-26-1092 | C8: 46137 | D8: 46167 | E8: 22400 | F8: =MAX(0,DATE(2026,5,14)-D8) | G8: =IF(F8<=30,E8,0) | H8: =IF(AND(F8>30,F8<=60),E8,0) | I8: =IF(AND(F8>60,F8<=90),E8,0) | J8: =IF(F8>90,E8,0)
A9: Adriatic Pumps doo | B9: INV-26-0998 | C9: 46042 | D9: 46072 | E9: 6800 | F9: =MAX(0,DATE(2026,5,14)-D9) | G9: =IF(F9<=30,E9,0) | H9: =IF(AND(F9>30,F9<=60),E9,0) | I9: =IF(AND(F9>60,F9<=90),E9,0) | J9: =IF(F9>90,E9,0)
A10: Adriatic Pumps doo | B10: INV-26-1015 | C10: 46071 | D10: 46101 | E10: 9200 | F10: =MAX(0,DATE(2026,5,14)-D10) | G10: =IF(F10<=30,E10,0) | H10: =IF(AND(F10>30,F10<=60),E10,0) | I10: =IF(AND(F10>60,F10<=90),E10,0) | J10: =IF(F10>90,E10,0)
A11: Helvetica Mechanik AG | B11: INV-26-1099 | C11: 46144 | D11: 46174 | E11: 16400 | F11: =MAX(0,DATE(2026,5,14)-D11) | G11: =IF(F11<=30,E11,0) | H11: =IF(AND(F11>30,F11<=60),E11,0) | I11: =IF(AND(F11>60,F11<=90),E11,0) | J11: =IF(F11>90,E11,0)
A12: TOTAL | E12: =SUM(E2:E11) | G12: =SUM(G2:G11) | H12: =SUM(H2:H11) | I12: =SUM(I2:I11) | J12: =SUM(J2:J11)

Sheet Dashboard
B2: Helios Manufacturing s.r.o. — Operations Snapshot
B3: Period: April 2026 · Reporting currency: EUR · Source workbook for Odoo Spreadsheet import test
B5: Net Revenue (period) | C5: ='P&L'!B7
B6: Gross Profit | C6: ='P&L'!B15
B7: Gross Margin % | C7: ='P&L'!B15/'P&L'!B7
B8: Operating Income (EBIT) | C8: ='P&L'!B28
B9: Net Income | C9: ='P&L'!B34
B10: Open Sales Orders (count) | C10: =COUNTIF('Sales Orders'!N:N,"Confirmed")+COUNTIF('Sales Orders'!N:N,"Quotation")
B11: Inventory Value | C11: ='Inventory'!J32
B12: AR Outstanding | C12: ='AR Aging'!E12
B13: AR Past Due (>30d) | C13: ='AR Aging'!H12+'AR Aging'!I12+'AR Aging'!J12
B14: Production Work Orders Open | C14: =COUNTIF('Production'!J:J,"In Progress")+COUNTIF('Production'!J:J,"Scheduled")
B15: Items Below Reorder Point | C15: =COUNTIF('Inventory'!H:H,"REORDER")
